liquidnn/__init__.py
liquidnn/liquidnetwork.py
liquidnn/liquidneuron.py
liquidnn-1.1.2.dist-info/licenses/License
liquidnn-1.1.2.dist-info/METADATA
liquidnn-1.1.2.dist-info/WHEEL
liquidnn-1.1.2.dist-info/top_level.txt
liquidnn-1.1.2.dist-info/RECORD
