Metadata-Version: 2.4
Name: liquidnn
Version: 1.1.2
Summary: A PyTorch based module for Liquid Networks
Author: Nakshatra Yadav
Author-email: nakshatrayadav1729@gmail.com
Classifier: Programming Language :: Python :: 3
Classifier: License :: OSI Approved :: MIT License
Classifier: Operating System :: OS Independent
License-File: License
Requires-Dist: torch
Dynamic: author
Dynamic: author-email
Dynamic: classifier
Dynamic: description
Dynamic: description-content-type
Dynamic: license-file
Dynamic: requires-dist
Dynamic: summary
